html_to_json_enhanced/__init__.py
html_to_json_enhanced/convert_html.py
html_to_json_enhanced/convert_html_tables.py
html_to_json_enhanced/utils/__init__.py
html_to_json_enhanced/utils/css_path.py
tests/utils/__init__.py
tests/utils/test_css_path.py
html_to_json_enhanced-1.0.5.dist-info/LICENSE
html_to_json_enhanced-1.0.5.dist-info/METADATA
html_to_json_enhanced-1.0.5.dist-info/WHEEL
html_to_json_enhanced-1.0.5.dist-info/top_level.txt
html_to_json_enhanced-1.0.5.dist-info/zip-safe
html_to_json_enhanced-1.0.5.dist-info/RECORD
