Metadata-Version: 2.1
Name: html-to-json-enhanced
Version: 1.0.5
Summary: Convert html to json.
Home-page: https://github.com/fhightower/html-to-json
Author: Marvin Zhang
Author-email: 
License: MIT License
Project-URL: Source, https://github.com/crawlab-team/html-to-json-enhanced
Project-URL: Tracker, https://github.com/crawlab-team/html-to-json/issues
Project-URL: PyPi, https://pypi.org/project/html-to-json-enhanced/
Keywords: html to json,html,json,conversion
Classifier: Development Status :: 4 - Beta
Classifier: Intended Audience :: Developers
Classifier: Intended Audience :: Information Technology
Classifier: License :: OSI Approved :: MIT License
Classifier: Natural Language :: English
Classifier: Programming Language :: Python :: 3
Classifier: Programming Language :: Python :: 3.6
Classifier: Programming Language :: Python :: 3.7
Classifier: Programming Language :: Python :: 3.8
Classifier: Programming Language :: Python :: 3.9
License-File: LICENSE
Requires-Dist: bs4
